om_helper/decorators.py
om_helper/exceptions.py
om_helper/helper.py
om_helper-0.0.17.dist-info/WHEEL
om_helper-0.0.17.dist-info/METADATA
om_helper-0.0.17.dist-info/RECORD
